Muteract/db.sqlite3
Muteract/main.py
Muteract/manage.py
Muteract/package-lock.json
Muteract/package.json
Muteract/start.sh
Muteract/tsconfig.json
Muteract/webpack-stats.json
Muteract/webpack.config.js
Muteract/MBFuzzLLM/__init__.py
Muteract/MBFuzzLLM/asgi.py
Muteract/MBFuzzLLM/db.sqlite3
Muteract/MBFuzzLLM/urls.py
Muteract/MBFuzzLLM/wsgi.py
Muteract/MBFuzzLLM/__pycache__/__init__.cpython-310.pyc
Muteract/MBFuzzLLM/__pycache__/settings.cpython-310.pyc
Muteract/MBFuzzLLM/__pycache__/urls.cpython-310.pyc
Muteract/MBFuzzLLM/__pycache__/wsgi.cpython-310.pyc
Muteract/MBFuzzLLM/settings/__init__.py
Muteract/MBFuzzLLM/settings/local.py
Muteract/MBFuzzLLM/settings/production.py
Muteract/MBFuzzLLM/settings/__pycache__/__init__.cpython-310.pyc
Muteract/MBFuzzLLM/settings/__pycache__/local.cpython-310.pyc
Muteract/frontend/__init__.py
Muteract/frontend/admin.py
Muteract/frontend/apps.py
Muteract/frontend/config.json
Muteract/frontend/llms.py
Muteract/frontend/metrics.py
Muteract/frontend/models.py
Muteract/frontend/tests.py
Muteract/frontend/urls.py
Muteract/frontend/views.py
Muteract/frontend/__pycache__/__init__.cpython-310.pyc
Muteract/frontend/__pycache__/admin.cpython-310.pyc
Muteract/frontend/__pycache__/apps.cpython-310.pyc
Muteract/frontend/__pycache__/llms.cpython-310.pyc
Muteract/frontend/__pycache__/metrics.cpython-310.pyc
Muteract/frontend/__pycache__/models.cpython-310.pyc
Muteract/frontend/__pycache__/urls.cpython-310.pyc
Muteract/frontend/__pycache__/views.cpython-310.pyc
Muteract/frontend/bin/radamsa
Muteract/frontend/migrations/__init__.py
Muteract/frontend/migrations/__pycache__/__init__.cpython-310.pyc
Muteract/frontend/src/ApiCalls.tsx
Muteract/frontend/src/App.css
Muteract/frontend/src/App.test.tsx
Muteract/frontend/src/App.tsx
Muteract/frontend/src/ChatPanel.tsx
Muteract/frontend/src/ComparisonModal.tsx
Muteract/frontend/src/FormComponents.tsx
Muteract/frontend/src/HelpComponent.tsx
Muteract/frontend/src/Models.tsx
Muteract/frontend/src/MutationPanel.tsx
muteract-0.1.3.dist-info/licenses/LICENSE
muteract-0.1.3.dist-info/METADATA
muteract-0.1.3.dist-info/WHEEL
muteract-0.1.3.dist-info/entry_points.txt
muteract-0.1.3.dist-info/top_level.txt
muteract-0.1.3.dist-info/RECORD
